{
  "schema": "blueprint_print_readiness_v1",
  "seed": "cubesat",
  "bed_mm": [
    220.0,
    220.0,
    250.0
  ],
  "verdict": "ok_to_print",
  "parts": [
    {
      "file": "fit_test_coupon.stl",
      "triangles": 2036,
      "size_mm": [
        71.0,
        16.0,
        15.0
      ],
      "volume_mm3": 4761.0,
      "non_manifold_edges": 0,
      "degenerate_triangles": 0,
      "checks": {
        "watertight": true,
        "positive_volume": true,
        "bed_fit": true,
        "low_degenerate": true
      },
      "do_not_print": false
    },
    {
      "file": "new-001_seg1_integrated_rail_frame_spine.stl",
      "triangles": 68,
      "size_mm": [
        96.0,
        96.0,
        165.0
      ],
      "volume_mm3": 72795.0,
      "non_manifold_edges": 0,
      "degenerate_triangles": 0,
      "checks": {
        "watertight": true,
        "positive_volume": true,
        "bed_fit": true,
        "low_degenerate": true
      },
      "do_not_print": false
    },
    {
      "file": "new-001_seg2_integrated_rail_frame_spine.stl",
      "triangles": 780,
      "size_mm": [
        96.0,
        96.0,
        165.0
      ],
      "volume_mm3": 72785.0,
      "non_manifold_edges": 0,
      "degenerate_triangles": 0,
      "checks": {
        "watertight": true,
        "positive_volume": true,
        "bed_fit": true,
        "low_degenerate": true
      },
      "do_not_print": false
    },
    {
      "file": "new-002_removable_service_panels.stl",
      "triangles": 12,
      "size_mm": [
        91.8,
        1.5,
        150.0
      ],
      "volume_mm3": 21332.0,
      "non_manifold_edges": 0,
      "degenerate_triangles": 0,
      "checks": {
        "watertight": true,
        "positive_volume": true,
        "bed_fit": true,
        "low_degenerate": true
      },
      "do_not_print": false
    },
    {
      "file": "new-003_seg1_board_shelf_and_standoff_ladder.stl",
      "triangles": 128,
      "size_mm": [
        73.7,
        17.6,
        130.0
      ],
      "volume_mm3": 165127.0,
      "non_manifold_edges": 0,
      "degenerate_triangles": 0,
      "checks": {
        "watertight": true,
        "positive_volume": true,
        "bed_fit": true,
        "low_degenerate": true
      },
      "do_not_print": false
    },
    {
      "file": "new-003_seg2_board_shelf_and_standoff_ladder.stl",
      "triangles": 128,
      "size_mm": [
        73.7,
        17.6,
        130.0
      ],
      "volume_mm3": 165127.0,
      "non_manifold_edges": 0,
      "degenerate_triangles": 0,
      "checks": {
        "watertight": true,
        "positive_volume": true,
        "bed_fit": true,
        "low_degenerate": true
      },
      "do_not_print": false
    },
    {
      "file": "new-004_replaceable_antenna_hinge_dummy_pair.stl",
      "triangles": 884,
      "size_mm": [
        7.8,
        7.8,
        18.0
      ],
      "volume_mm3": 862.0,
      "non_manifold_edges": 0,
      "degenerate_triangles": 0,
      "checks": {
        "watertight": true,
        "positive_volume": true,
        "bed_fit": true,
        "low_degenerate": true
      },
      "do_not_print": false
    }
  ]
}