{
 "version": "bp-assembly-v1-generated",
 "target": "arm_6dof",
 "joints": [
  {
   "id": "J1",
   "partA": "p1",
   "partB": "p10",
   "mate": "face",
   "clearance_mm": 0.25,
   "note": "mounting: motor_mounting_pattern"
  },
  {
   "id": "J2",
   "partA": "p3",
   "partB": "p2",
   "mate": "face",
   "clearance_mm": 0.25,
   "note": "mounting flange: Base Flange"
  },
  {
   "id": "J3",
   "partA": "p3",
   "partB": "p4",
   "mate": "face",
   "clearance_mm": 0.25,
   "note": "mounting flange: Tool Flange"
  },
  {
   "id": "J4",
   "partA": "p5",
   "partB": "p1",
   "mate": "face",
   "clearance_mm": 0.25,
   "note": "service_access_cut: harness_cut"
  }
 ],
 "fasteners": [],
 "hardware_bom": []
}