{
 "version": "bp-assembly-v1-generated",
 "target": "cubesat_3u",
 "joints": [
  {
   "id": "J1",
   "partA": "p6",
   "partB": "p1",
   "mate": "face",
   "clearance_mm": 0.25,
   "note": "mounting datum: Payload Mounting Holes"
  },
  {
   "id": "J2",
   "partA": "p6",
   "partB": "p10",
   "mate": "face",
   "clearance_mm": 0.25,
   "note": "connector mate: Payload Data Connector"
  },
  {
   "id": "J3",
   "partA": "p6",
   "partB": "p1",
   "mate": "face",
   "clearance_mm": 0.25,
   "note": "harness passthrough: Cable Exit Grommet"
  },
  {
   "id": "J4",
   "partA": "p9",
   "partB": "p1",
   "mate": "face",
   "clearance_mm": 0.25,
   "note": "mounting: mounting_datum_A"
  },
  {
   "id": "J5",
   "partA": "p9",
   "partB": "p1",
   "mate": "face",
   "clearance_mm": 0.25,
   "note": "thermal: cooling_fin_interface"
  },
  {
   "id": "J6",
   "partA": "p10",
   "partB": "p1",
   "mate": "face",
   "clearance_mm": 0.25,
   "note": "mounting: Mounting_Holes"
  },
  {
   "id": "J7",
   "partA": "p10",
   "partB": "p6",
   "mate": "face",
   "clearance_mm": 0.25,
   "note": "data: Payload_Connector"
  }
 ],
 "fasteners": [],
 "hardware_bom": []
}